claude.py
Claude/__init__.py
Claude/claude.py
claude2-1.1.5.dist-info/LICENSE
claude2-1.1.5.dist-info/METADATA
claude2-1.1.5.dist-info/WHEEL
claude2-1.1.5.dist-info/top_level.txt
claude2-1.1.5.dist-info/RECORD
