Metadata-Version: 2.1
Name: claude2
Version: 1.1.5
Summary: A Python package provides an unofficial api for interacting with the Claude from Anthropic
Home-page: https://github.com/Nipun1212/Claude_api
Author: Nipun
Author-email: nipunbhatia06@gmail.com
License: MIT
Keywords: claude,ai,claude-ai,API,requests,chatbot
Classifier: Development Status :: 3 - Alpha
Classifier: Intended Audience :: Developers
Classifier: License :: OSI Approved :: MIT License
Classifier: Programming Language :: Python :: 3.7
Classifier: Programming Language :: Python :: 3.8
Classifier: Programming Language :: Python :: 3.9
Requires-Python: >=3.7
License-File: LICENSE
Requires-Dist: requests
Requires-Dist: curl-cffi
